pastypy/__init__.py
pastypy/asyncio.py
pastypy/sync.py
pastypy-1.0.3.post1.dist-info/LICENSE
pastypy-1.0.3.post1.dist-info/METADATA
pastypy-1.0.3.post1.dist-info/WHEEL
pastypy-1.0.3.post1.dist-info/RECORD
